uppaalpy/__init__.py
uppaalpy/classes/__init__.py
uppaalpy/classes/class_tests/__init__.py
uppaalpy/classes/class_tests/constraint_cache_xml_files/test01.xml
uppaalpy/classes/class_tests/constraint_xml_files/test01.xml
uppaalpy/classes/class_tests/constraint_xml_files/test02.xml
uppaalpy/classes/class_tests/constraint_xml_files/test03.xml
uppaalpy/classes/class_tests/constraint_xml_files/test04.xml
uppaalpy/classes/class_tests/constraint_xml_files/test05.xml
uppaalpy/classes/class_tests/constraint_xml_files/test06.xml
uppaalpy/classes/class_tests/constraint_xml_files/test07.xml
uppaalpy/classes/class_tests/helpers.py
uppaalpy/classes/class_tests/label_xml_files/test01.xml
uppaalpy/classes/class_tests/label_xml_files/test02.xml
uppaalpy/classes/class_tests/label_xml_files/test03.xml
uppaalpy/classes/class_tests/label_xml_files/test04.xml
uppaalpy/classes/class_tests/label_xml_files/test05.xml
uppaalpy/classes/class_tests/label_xml_files/test06.xml
uppaalpy/classes/class_tests/label_xml_files/test07.xml
uppaalpy/classes/class_tests/label_xml_files/test08.xml
uppaalpy/classes/class_tests/label_xml_files/test09.xml
uppaalpy/classes/class_tests/nta_xml_files/big_nta.xml
uppaalpy/classes/class_tests/nta_xml_files/small_nta.xml
uppaalpy/classes/class_tests/nta_xml_files/test3.xml
uppaalpy/classes/class_tests/nta_xml_files/test4.xml
uppaalpy/classes/class_tests/random_changers.py
uppaalpy/classes/class_tests/template_xml_files/test1.xml
uppaalpy/classes/class_tests/template_xml_files/test2.xml
uppaalpy/classes/class_tests/template_xml_files/test3.xml
uppaalpy/classes/class_tests/template_xml_files/test4.xml
uppaalpy/classes/class_tests/template_xml_files/test5.xml
uppaalpy/classes/class_tests/template_xml_files/test6.xml
uppaalpy/classes/class_tests/test_constraint_cache.py
uppaalpy/classes/class_tests/test_constraint_change.py
uppaalpy/classes/class_tests/test_constraint_change_cases.py
uppaalpy/classes/class_tests/test_context.py
uppaal_py-0.0.4.dist-info/LICENSE
uppaal_py-0.0.4.dist-info/WHEEL
uppaal_py-0.0.4.dist-info/METADATA
uppaal_py-0.0.4.dist-info/RECORD
