Metadata-Version: 2.1
Name: uppaal-py
Version: 0.0.4
Summary: UPPAAL wrapper for Python.
Home-page: https://github.com/koluacik/uppaal-py
License: MIT
Author: Deniz Koluaçık
Author-email: koluacik@disroot.org
Requires-Python: >=3.8,<4.0
Classifier: License :: OSI Approved :: MIT License
Classifier: Programming Language :: Python :: 3
Classifier: Programming Language :: Python :: 3.8
Classifier: Programming Language :: Python :: 3.9
Requires-Dist: lxml (>=4.6.2)
Requires-Dist: networkx (>=2.5)
Requires-Dist: ortools (>=8.1.8487)
